{
  "connectionName" : "www.vk.com",
  "connectionPort" : 443,
  "SNI" : "www.vk.com",
  "TLSv1.0" : {
    "suiteSelection" : "server",
    "suites" : [
      {
        "id" : 49172,
        "name" : "ECDHE_RSA_WITH_AES_256_CBC_SHA",
        "strength" : 3,
        "forwardSecrecy" : true,
        "anonymous" : false,
        "serverKeyType" : "RSA"
      },
      {
        "id" : 49171,
        "name" : "ECDHE_RSA_WITH_AES_128_CBC_SHA",
        "strength" : 3,
        "forwardSecrecy" : true,
        "anonymous" : false,
        "serverKeyType" : "RSA"
      },
      {
        "id" : 57,
        "name" : "DHE_RSA_WITH_AES_256_CBC_SHA",
        "strength" : 3,
        "forwardSecrecy" : true,
        "anonymous" : false,
        "serverKeyType" : "RSA"
      },
      {
        "id" : 51,
        "name" : "DHE_RSA_WITH_AES_128_CBC_SHA",
        "strength" : 3,
        "forwardSecrecy" : true,
        "anonymous" : false,
        "serverKeyType" : "RSA"
      },
      {
        "id" : 49170,
        "name" : "ECDHE_RSA_WITH_3DES_EDE_CBC_SHA",
        "strength" : 3,
        "forwardSecrecy" : true,
        "anonymous" : false,
        "serverKeyType" : "RSA"
      },
      {
        "id" : 22,
        "name" : "DHE_RSA_WITH_3DES_EDE_CBC_SHA",
        "strength" : 3,
        "forwardSecrecy" : true,
        "anonymous" : false,
        "serverKeyType" : "RSA"
      },
      {
        "id" : 53,
        "name" : "RSA_WITH_AES_256_CBC_SHA",
        "strength" : 3,
        "forwardSecrecy" : false,
        "anonymous" : false,
        "serverKeyType" : "RSA"
      },
      {
        "id" : 47,
        "name" : "RSA_WITH_AES_128_CBC_SHA",
        "strength" : 3,
        "forwardSecrecy" : false,
        "anonymous" : false,
        "serverKeyType" : "RSA"
      },
      {
        "id" : 10,
        "name" : "RSA_WITH_3DES_EDE_CBC_SHA",
        "strength" : 3,
        "forwardSecrecy" : false,
        "anonymous" : false,
        "serverKeyType" : "RSA"
      },
      {
        "id" : 136,
        "name" : "DHE_RSA_WITH_CAMELLIA_256_CBC_SHA",
        "strength" : 3,
        "forwardSecrecy" : true,
        "anonymous" : false,
        "serverKeyType" : "RSA"
      },
      {
        "id" : 132,
        "name" : "RSA_WITH_CAMELLIA_256_CBC_SHA",
        "strength" : 3,
        "forwardSecrecy" : false,
        "anonymous" : false,
        "serverKeyType" : "RSA"
      },
      {
        "id" : 69,
        "name" : "DHE_RSA_WITH_CAMELLIA_128_CBC_SHA",
        "strength" : 3,
        "forwardSecrecy" : true,
        "anonymous" : false,
        "serverKeyType" : "RSA"
      },
      {
        "id" : 65,
        "name" : "RSA_WITH_CAMELLIA_128_CBC_SHA",
        "strength" : 3,
        "forwardSecrecy" : false,
        "anonymous" : false,
        "serverKeyType" : "RSA"
      }
    ]
  },
  "TLSv1.1" : {
    "suiteSelection" : "server",
    "suites" : [
      {
        "id" : 49172,
        "name" : "ECDHE_RSA_WITH_AES_256_CBC_SHA",
        "strength" : 3,
        "forwardSecrecy" : true,
        "anonymous" : false,
        "serverKeyType" : "RSA"
      },
      {
        "id" : 49171,
        "name" : "ECDHE_RSA_WITH_AES_128_CBC_SHA",
        "strength" : 3,
        "forwardSecrecy" : true,
        "anonymous" : false,
        "serverKeyType" : "RSA"
      },
      {
        "id" : 57,
        "name" : "DHE_RSA_WITH_AES_256_CBC_SHA",
        "strength" : 3,
        "forwardSecrecy" : true,
        "anonymous" : false,
        "serverKeyType" : "RSA"
      },
      {
        "id" : 51,
        "name" : "DHE_RSA_WITH_AES_128_CBC_SHA",
        "strength" : 3,
        "forwardSecrecy" : true,
        "anonymous" : false,
        "serverKeyType" : "RSA"
      },
      {
        "id" : 49170,
        "name" : "ECDHE_RSA_WITH_3DES_EDE_CBC_SHA",
        "strength" : 3,
        "forwardSecrecy" : true,
        "anonymous" : false,
        "serverKeyType" : "RSA"
      },
      {
        "id" : 22,
        "name" : "DHE_RSA_WITH_3DES_EDE_CBC_SHA",
        "strength" : 3,
        "forwardSecrecy" : true,
        "anonymous" : false,
        "serverKeyType" : "RSA"
      },
      {
        "id" : 53,
        "name" : "RSA_WITH_AES_256_CBC_SHA",
        "strength" : 3,
        "forwardSecrecy" : false,
        "anonymous" : false,
        "serverKeyType" : "RSA"
      },
      {
        "id" : 47,
        "name" : "RSA_WITH_AES_128_CBC_SHA",
        "strength" : 3,
        "forwardSecrecy" : false,
        "anonymous" : false,
        "serverKeyType" : "RSA"
      },
      {
        "id" : 10,
        "name" : "RSA_WITH_3DES_EDE_CBC_SHA",
        "strength" : 3,
        "forwardSecrecy" : false,
        "anonymous" : false,
        "serverKeyType" : "RSA"
      },
      {
        "id" : 136,
        "name" : "DHE_RSA_WITH_CAMELLIA_256_CBC_SHA",
        "strength" : 3,
        "forwardSecrecy" : true,
        "anonymous" : false,
        "serverKeyType" : "RSA"
      },
      {
        "id" : 132,
        "name" : "RSA_WITH_CAMELLIA_256_CBC_SHA",
        "strength" : 3,
        "forwardSecrecy" : false,
        "anonymous" : false,
        "serverKeyType" : "RSA"
      },
      {
        "id" : 69,
        "name" : "DHE_RSA_WITH_CAMELLIA_128_CBC_SHA",
        "strength" : 3,
        "forwardSecrecy" : true,
        "anonymous" : false,
        "serverKeyType" : "RSA"
      },
      {
        "id" : 65,
        "name" : "RSA_WITH_CAMELLIA_128_CBC_SHA",
        "strength" : 3,
        "forwardSecrecy" : false,
        "anonymous" : false,
        "serverKeyType" : "RSA"
      }
    ]
  },
  "TLSv1.2" : {
    "suiteSelection" : "server",
    "suites" : [
      {
        "id" : 49200,
        "name" : "ECDHE_RSA_WITH_AES_256_GCM_SHA384",
        "strength" : 3,
        "forwardSecrecy" : true,
        "anonymous" : false,
        "serverKeyType" : "RSA"
      },
      {
        "id" : 49199,
        "name" : "ECDHE_RSA_WITH_AES_128_GCM_SHA256",
        "strength" : 3,
        "forwardSecrecy" : true,
        "anonymous" : false,
        "serverKeyType" : "RSA"
      },
      {
        "id" : 159,
        "name" : "DHE_RSA_WITH_AES_256_GCM_SHA384",
        "strength" : 3,
        "forwardSecrecy" : true,
        "anonymous" : false,
        "serverKeyType" : "RSA"
      },
      {
        "id" : 158,
        "name" : "DHE_RSA_WITH_AES_128_GCM_SHA256",
        "strength" : 3,
        "forwardSecrecy" : true,
        "anonymous" : false,
        "serverKeyType" : "RSA"
      },
      {
        "id" : 49192,
        "name" : "ECDHE_RSA_WITH_AES_256_CBC_SHA384",
        "strength" : 3,
        "forwardSecrecy" : true,
        "anonymous" : false,
        "serverKeyType" : "RSA"
      },
      {
        "id" : 49191,
        "name" : "ECDHE_RSA_WITH_AES_128_CBC_SHA256",
        "strength" : 3,
        "forwardSecrecy" : true,
        "anonymous" : false,
        "serverKeyType" : "RSA"
      },
      {
        "id" : 49172,
        "name" : "ECDHE_RSA_WITH_AES_256_CBC_SHA",
        "strength" : 3,
        "forwardSecrecy" : true,
        "anonymous" : false,
        "serverKeyType" : "RSA"
      },
      {
        "id" : 49171,
        "name" : "ECDHE_RSA_WITH_AES_128_CBC_SHA",
        "strength" : 3,
        "forwardSecrecy" : true,
        "anonymous" : false,
        "serverKeyType" : "RSA"
      },
      {
        "id" : 107,
        "name" : "DHE_RSA_WITH_AES_256_CBC_SHA256",
        "strength" : 3,
        "forwardSecrecy" : true,
        "anonymous" : false,
        "serverKeyType" : "RSA"
      },
      {
        "id" : 103,
        "name" : "DHE_RSA_WITH_AES_128_CBC_SHA256",
        "strength" : 3,
        "forwardSecrecy" : true,
        "anonymous" : false,
        "serverKeyType" : "RSA"
      },
      {
        "id" : 57,
        "name" : "DHE_RSA_WITH_AES_256_CBC_SHA",
        "strength" : 3,
        "forwardSecrecy" : true,
        "anonymous" : false,
        "serverKeyType" : "RSA"
      },
      {
        "id" : 51,
        "name" : "DHE_RSA_WITH_AES_128_CBC_SHA",
        "strength" : 3,
        "forwardSecrecy" : true,
        "anonymous" : false,
        "serverKeyType" : "RSA"
      },
      {
        "id" : 49170,
        "name" : "ECDHE_RSA_WITH_3DES_EDE_CBC_SHA",
        "strength" : 3,
        "forwardSecrecy" : true,
        "anonymous" : false,
        "serverKeyType" : "RSA"
      },
      {
        "id" : 22,
        "name" : "DHE_RSA_WITH_3DES_EDE_CBC_SHA",
        "strength" : 3,
        "forwardSecrecy" : true,
        "anonymous" : false,
        "serverKeyType" : "RSA"
      },
      {
        "id" : 157,
        "name" : "RSA_WITH_AES_256_GCM_SHA384",
        "strength" : 3,
        "forwardSecrecy" : false,
        "anonymous" : false,
        "serverKeyType" : "RSA"
      },
      {
        "id" : 156,
        "name" : "RSA_WITH_AES_128_GCM_SHA256",
        "strength" : 3,
        "forwardSecrecy" : false,
        "anonymous" : false,
        "serverKeyType" : "RSA"
      },
      {
        "id" : 61,
        "name" : "RSA_WITH_AES_256_CBC_SHA256",
        "strength" : 3,
        "forwardSecrecy" : false,
        "anonymous" : false,
        "serverKeyType" : "RSA"
      },
      {
        "id" : 60,
        "name" : "RSA_WITH_AES_128_CBC_SHA256",
        "strength" : 3,
        "forwardSecrecy" : false,
        "anonymous" : false,
        "serverKeyType" : "RSA"
      },
      {
        "id" : 53,
        "name" : "RSA_WITH_AES_256_CBC_SHA",
        "strength" : 3,
        "forwardSecrecy" : false,
        "anonymous" : false,
        "serverKeyType" : "RSA"
      },
      {
        "id" : 47,
        "name" : "RSA_WITH_AES_128_CBC_SHA",
        "strength" : 3,
        "forwardSecrecy" : false,
        "anonymous" : false,
        "serverKeyType" : "RSA"
      },
      {
        "id" : 10,
        "name" : "RSA_WITH_3DES_EDE_CBC_SHA",
        "strength" : 3,
        "forwardSecrecy" : false,
        "anonymous" : false,
        "serverKeyType" : "RSA"
      },
      {
        "id" : 136,
        "name" : "DHE_RSA_WITH_CAMELLIA_256_CBC_SHA",
        "strength" : 3,
        "forwardSecrecy" : true,
        "anonymous" : false,
        "serverKeyType" : "RSA"
      },
      {
        "id" : 132,
        "name" : "RSA_WITH_CAMELLIA_256_CBC_SHA",
        "strength" : 3,
        "forwardSecrecy" : false,
        "anonymous" : false,
        "serverKeyType" : "RSA"
      },
      {
        "id" : 69,
        "name" : "DHE_RSA_WITH_CAMELLIA_128_CBC_SHA",
        "strength" : 3,
        "forwardSecrecy" : true,
        "anonymous" : false,
        "serverKeyType" : "RSA"
      },
      {
        "id" : 65,
        "name" : "RSA_WITH_CAMELLIA_128_CBC_SHA",
        "strength" : 3,
        "forwardSecrecy" : false,
        "anonymous" : false,
        "serverKeyType" : "RSA"
      }
    ]
  },
  "ssl3Chains" : [
    {
      "length" : 4,
      "decoded" : true,
      "namesMatch" : true,
      "includesRoot" : true,
      "signHashes" : [
        "SHA-256"
      ],
      "certificates" : [
        {
          "thumbprint" : "FB9BAF57F4467CBF9080E57A186E15A30F11DD9F",
          "decodable" : true,
          "serialHex" : "6C7C988A18C595FD",
          "subject" : "CN=*.vk.com,OU=Domain Control Validated",
          "issuer" : "CN=Go Daddy Secure Certificate Authority - G2,OU=http://certs.godaddy.com/repository/,O=GoDaddy.com\\, Inc.,L=Scottsdale,ST=Arizona,C=US",
          "validFrom" : "2015-09-04 21:17:41 UTC",
          "validTo" : "2018-09-16 11:56:55 UTC",
          "keyType" : "RSA",
          "keySize" : 2048,
          "signHash" : "SHA-256",
          "selfIssued" : false,
          "serverNames" : [
            "*.vk.com",
            "vk.com"
          ]
        },
        {
          "thumbprint" : "27AC9369FAF25207BB2627CEFACCBE4EF9C319B8",
          "decodable" : true,
          "serialHex" : "07",
          "subject" : "CN=Go Daddy Secure Certificate Authority - G2,OU=http://certs.godaddy.com/repository/,O=GoDaddy.com\\, Inc.,L=Scottsdale,ST=Arizona,C=US",
          "issuer" : "CN=Go Daddy Root Certificate Authority - G2,O=GoDaddy.com\\, Inc.,L=Scottsdale,ST=Arizona,C=US",
          "validFrom" : "2011-05-03 07:00:00 UTC",
          "validTo" : "2031-05-03 07:00:00 UTC",
          "keyType" : "RSA",
          "keySize" : 2048,
          "signHash" : "SHA-256",
          "selfIssued" : false
        },
        {
          "thumbprint" : "340B2880F446FCC04E59ED33F52B3D08D6242964",
          "decodable" : true,
          "serialHex" : "1BE715",
          "subject" : "CN=Go Daddy Root Certificate Authority - G2,O=GoDaddy.com\\, Inc.,L=Scottsdale,ST=Arizona,C=US",
          "issuer" : "OU=Go Daddy Class 2 Certification Authority,O=The Go Daddy Group\\, Inc.,C=US",
          "validFrom" : "2014-01-01 07:00:00 UTC",
          "validTo" : "2031-05-30 07:00:00 UTC",
          "keyType" : "RSA",
          "keySize" : 2048,
          "signHash" : "SHA-256",
          "selfIssued" : false
        },
        {
          "thumbprint" : "2796BAE63F1801E277261BA0D77770028F20EEE4",
          "decodable" : true,
          "serialHex" : "00",
          "subject" : "OU=Go Daddy Class 2 Certification Authority,O=The Go Daddy Group\\, Inc.,C=US",
          "issuer" : "OU=Go Daddy Class 2 Certification Authority,O=The Go Daddy Group\\, Inc.,C=US",
          "validFrom" : "2004-06-29 17:06:20 UTC",
          "validTo" : "2034-06-29 17:06:20 UTC",
          "keyType" : "RSA",
          "keySize" : 2048,
          "signHash" : "SHA-1",
          "selfIssued" : true
        }
      ]
    }
  ],
  "deflateCompress" : false,
  "serverTime" : "random",
  "secureRenegotiation" : true,
  "minDHSize" : 2048,
  "minECSizeExt" : 256,
  "namedCurves" : [
    {
      "name" : "secp256r1 (P-256)",
      "size" : 256,
      "spontaneous" : false
    }
  ],
  "warnings" : [
    {
      "id" : "CS006",
      "text" : "Server supports cipher suites with no forward secrecy."
    }
  ]
}
