{
  "connectionName" : "www.javatpoint.com",
  "connectionPort" : 443,
  "SNI" : "www.javatpoint.com",
  "TLSv1.0" : {
    "suiteSelection" : "client",
    "suites" : [
      {
        "id" : 4,
        "name" : "RSA_WITH_RC4_128_MD5",
        "strength" : 3,
        "forwardSecrecy" : false,
        "anonymous" : false,
        "serverKeyType" : "RSA"
      },
      {
        "id" : 5,
        "name" : "RSA_WITH_RC4_128_SHA",
        "strength" : 3,
        "forwardSecrecy" : false,
        "anonymous" : false,
        "serverKeyType" : "RSA"
      },
      {
        "id" : 7,
        "name" : "RSA_WITH_IDEA_CBC_SHA",
        "strength" : 3,
        "forwardSecrecy" : false,
        "anonymous" : false,
        "serverKeyType" : "RSA"
      },
      {
        "id" : 10,
        "name" : "RSA_WITH_3DES_EDE_CBC_SHA",
        "strength" : 3,
        "forwardSecrecy" : false,
        "anonymous" : false,
        "serverKeyType" : "RSA"
      },
      {
        "id" : 47,
        "name" : "RSA_WITH_AES_128_CBC_SHA",
        "strength" : 3,
        "forwardSecrecy" : false,
        "anonymous" : false,
        "serverKeyType" : "RSA"
      },
      {
        "id" : 53,
        "name" : "RSA_WITH_AES_256_CBC_SHA",
        "strength" : 3,
        "forwardSecrecy" : false,
        "anonymous" : false,
        "serverKeyType" : "RSA"
      },
      {
        "id" : 65,
        "name" : "RSA_WITH_CAMELLIA_128_CBC_SHA",
        "strength" : 3,
        "forwardSecrecy" : false,
        "anonymous" : false,
        "serverKeyType" : "RSA"
      },
      {
        "id" : 132,
        "name" : "RSA_WITH_CAMELLIA_256_CBC_SHA",
        "strength" : 3,
        "forwardSecrecy" : false,
        "anonymous" : false,
        "serverKeyType" : "RSA"
      },
      {
        "id" : 150,
        "name" : "RSA_WITH_SEED_CBC_SHA",
        "strength" : 3,
        "forwardSecrecy" : false,
        "anonymous" : false,
        "serverKeyType" : "RSA"
      },
      {
        "id" : 49169,
        "name" : "ECDHE_RSA_WITH_RC4_128_SHA",
        "strength" : 3,
        "forwardSecrecy" : true,
        "anonymous" : false,
        "serverKeyType" : "RSA"
      },
      {
        "id" : 49170,
        "name" : "ECDHE_RSA_WITH_3DES_EDE_CBC_SHA",
        "strength" : 3,
        "forwardSecrecy" : true,
        "anonymous" : false,
        "serverKeyType" : "RSA"
      },
      {
        "id" : 49171,
        "name" : "ECDHE_RSA_WITH_AES_128_CBC_SHA",
        "strength" : 3,
        "forwardSecrecy" : true,
        "anonymous" : false,
        "serverKeyType" : "RSA"
      },
      {
        "id" : 49172,
        "name" : "ECDHE_RSA_WITH_AES_256_CBC_SHA",
        "strength" : 3,
        "forwardSecrecy" : true,
        "anonymous" : false,
        "serverKeyType" : "RSA"
      },
      {
        "id" : 49174,
        "name" : "ECDH_anon_WITH_RC4_128_SHA",
        "strength" : 3,
        "forwardSecrecy" : true,
        "anonymous" : true,
        "serverKeyType" : "none"
      },
      {
        "id" : 49175,
        "name" : "ECDH_anon_WITH_3DES_EDE_CBC_SHA",
        "strength" : 3,
        "forwardSecrecy" : true,
        "anonymous" : true,
        "serverKeyType" : "none"
      },
      {
        "id" : 49176,
        "name" : "ECDH_anon_WITH_AES_128_CBC_SHA",
        "strength" : 3,
        "forwardSecrecy" : true,
        "anonymous" : true,
        "serverKeyType" : "none"
      },
      {
        "id" : 49177,
        "name" : "ECDH_anon_WITH_AES_256_CBC_SHA",
        "strength" : 3,
        "forwardSecrecy" : true,
        "anonymous" : true,
        "serverKeyType" : "none"
      }
    ]
  },
  "TLSv1.1" : {
    "suiteSelection" : "client",
    "suites" : [
      {
        "id" : 4,
        "name" : "RSA_WITH_RC4_128_MD5",
        "strength" : 3,
        "forwardSecrecy" : false,
        "anonymous" : false,
        "serverKeyType" : "RSA"
      },
      {
        "id" : 5,
        "name" : "RSA_WITH_RC4_128_SHA",
        "strength" : 3,
        "forwardSecrecy" : false,
        "anonymous" : false,
        "serverKeyType" : "RSA"
      },
      {
        "id" : 7,
        "name" : "RSA_WITH_IDEA_CBC_SHA",
        "strength" : 3,
        "forwardSecrecy" : false,
        "anonymous" : false,
        "serverKeyType" : "RSA"
      },
      {
        "id" : 10,
        "name" : "RSA_WITH_3DES_EDE_CBC_SHA",
        "strength" : 3,
        "forwardSecrecy" : false,
        "anonymous" : false,
        "serverKeyType" : "RSA"
      },
      {
        "id" : 47,
        "name" : "RSA_WITH_AES_128_CBC_SHA",
        "strength" : 3,
        "forwardSecrecy" : false,
        "anonymous" : false,
        "serverKeyType" : "RSA"
      },
      {
        "id" : 53,
        "name" : "RSA_WITH_AES_256_CBC_SHA",
        "strength" : 3,
        "forwardSecrecy" : false,
        "anonymous" : false,
        "serverKeyType" : "RSA"
      },
      {
        "id" : 65,
        "name" : "RSA_WITH_CAMELLIA_128_CBC_SHA",
        "strength" : 3,
        "forwardSecrecy" : false,
        "anonymous" : false,
        "serverKeyType" : "RSA"
      },
      {
        "id" : 132,
        "name" : "RSA_WITH_CAMELLIA_256_CBC_SHA",
        "strength" : 3,
        "forwardSecrecy" : false,
        "anonymous" : false,
        "serverKeyType" : "RSA"
      },
      {
        "id" : 150,
        "name" : "RSA_WITH_SEED_CBC_SHA",
        "strength" : 3,
        "forwardSecrecy" : false,
        "anonymous" : false,
        "serverKeyType" : "RSA"
      },
      {
        "id" : 49169,
        "name" : "ECDHE_RSA_WITH_RC4_128_SHA",
        "strength" : 3,
        "forwardSecrecy" : true,
        "anonymous" : false,
        "serverKeyType" : "RSA"
      },
      {
        "id" : 49170,
        "name" : "ECDHE_RSA_WITH_3DES_EDE_CBC_SHA",
        "strength" : 3,
        "forwardSecrecy" : true,
        "anonymous" : false,
        "serverKeyType" : "RSA"
      },
      {
        "id" : 49171,
        "name" : "ECDHE_RSA_WITH_AES_128_CBC_SHA",
        "strength" : 3,
        "forwardSecrecy" : true,
        "anonymous" : false,
        "serverKeyType" : "RSA"
      },
      {
        "id" : 49172,
        "name" : "ECDHE_RSA_WITH_AES_256_CBC_SHA",
        "strength" : 3,
        "forwardSecrecy" : true,
        "anonymous" : false,
        "serverKeyType" : "RSA"
      },
      {
        "id" : 49174,
        "name" : "ECDH_anon_WITH_RC4_128_SHA",
        "strength" : 3,
        "forwardSecrecy" : true,
        "anonymous" : true,
        "serverKeyType" : "none"
      },
      {
        "id" : 49175,
        "name" : "ECDH_anon_WITH_3DES_EDE_CBC_SHA",
        "strength" : 3,
        "forwardSecrecy" : true,
        "anonymous" : true,
        "serverKeyType" : "none"
      },
      {
        "id" : 49176,
        "name" : "ECDH_anon_WITH_AES_128_CBC_SHA",
        "strength" : 3,
        "forwardSecrecy" : true,
        "anonymous" : true,
        "serverKeyType" : "none"
      },
      {
        "id" : 49177,
        "name" : "ECDH_anon_WITH_AES_256_CBC_SHA",
        "strength" : 3,
        "forwardSecrecy" : true,
        "anonymous" : true,
        "serverKeyType" : "none"
      }
    ]
  },
  "TLSv1.2" : {
    "suiteSelection" : "client",
    "suites" : [
      {
        "id" : 4,
        "name" : "RSA_WITH_RC4_128_MD5",
        "strength" : 3,
        "forwardSecrecy" : false,
        "anonymous" : false,
        "serverKeyType" : "RSA"
      },
      {
        "id" : 5,
        "name" : "RSA_WITH_RC4_128_SHA",
        "strength" : 3,
        "forwardSecrecy" : false,
        "anonymous" : false,
        "serverKeyType" : "RSA"
      },
      {
        "id" : 7,
        "name" : "RSA_WITH_IDEA_CBC_SHA",
        "strength" : 3,
        "forwardSecrecy" : false,
        "anonymous" : false,
        "serverKeyType" : "RSA"
      },
      {
        "id" : 10,
        "name" : "RSA_WITH_3DES_EDE_CBC_SHA",
        "strength" : 3,
        "forwardSecrecy" : false,
        "anonymous" : false,
        "serverKeyType" : "RSA"
      },
      {
        "id" : 47,
        "name" : "RSA_WITH_AES_128_CBC_SHA",
        "strength" : 3,
        "forwardSecrecy" : false,
        "anonymous" : false,
        "serverKeyType" : "RSA"
      },
      {
        "id" : 53,
        "name" : "RSA_WITH_AES_256_CBC_SHA",
        "strength" : 3,
        "forwardSecrecy" : false,
        "anonymous" : false,
        "serverKeyType" : "RSA"
      },
      {
        "id" : 60,
        "name" : "RSA_WITH_AES_128_CBC_SHA256",
        "strength" : 3,
        "forwardSecrecy" : false,
        "anonymous" : false,
        "serverKeyType" : "RSA"
      },
      {
        "id" : 61,
        "name" : "RSA_WITH_AES_256_CBC_SHA256",
        "strength" : 3,
        "forwardSecrecy" : false,
        "anonymous" : false,
        "serverKeyType" : "RSA"
      },
      {
        "id" : 65,
        "name" : "RSA_WITH_CAMELLIA_128_CBC_SHA",
        "strength" : 3,
        "forwardSecrecy" : false,
        "anonymous" : false,
        "serverKeyType" : "RSA"
      },
      {
        "id" : 132,
        "name" : "RSA_WITH_CAMELLIA_256_CBC_SHA",
        "strength" : 3,
        "forwardSecrecy" : false,
        "anonymous" : false,
        "serverKeyType" : "RSA"
      },
      {
        "id" : 150,
        "name" : "RSA_WITH_SEED_CBC_SHA",
        "strength" : 3,
        "forwardSecrecy" : false,
        "anonymous" : false,
        "serverKeyType" : "RSA"
      },
      {
        "id" : 156,
        "name" : "RSA_WITH_AES_128_GCM_SHA256",
        "strength" : 3,
        "forwardSecrecy" : false,
        "anonymous" : false,
        "serverKeyType" : "RSA"
      },
      {
        "id" : 157,
        "name" : "RSA_WITH_AES_256_GCM_SHA384",
        "strength" : 3,
        "forwardSecrecy" : false,
        "anonymous" : false,
        "serverKeyType" : "RSA"
      },
      {
        "id" : 49169,
        "name" : "ECDHE_RSA_WITH_RC4_128_SHA",
        "strength" : 3,
        "forwardSecrecy" : true,
        "anonymous" : false,
        "serverKeyType" : "RSA"
      },
      {
        "id" : 49170,
        "name" : "ECDHE_RSA_WITH_3DES_EDE_CBC_SHA",
        "strength" : 3,
        "forwardSecrecy" : true,
        "anonymous" : false,
        "serverKeyType" : "RSA"
      },
      {
        "id" : 49171,
        "name" : "ECDHE_RSA_WITH_AES_128_CBC_SHA",
        "strength" : 3,
        "forwardSecrecy" : true,
        "anonymous" : false,
        "serverKeyType" : "RSA"
      },
      {
        "id" : 49172,
        "name" : "ECDHE_RSA_WITH_AES_256_CBC_SHA",
        "strength" : 3,
        "forwardSecrecy" : true,
        "anonymous" : false,
        "serverKeyType" : "RSA"
      },
      {
        "id" : 49174,
        "name" : "ECDH_anon_WITH_RC4_128_SHA",
        "strength" : 3,
        "forwardSecrecy" : true,
        "anonymous" : true,
        "serverKeyType" : "none"
      },
      {
        "id" : 49175,
        "name" : "ECDH_anon_WITH_3DES_EDE_CBC_SHA",
        "strength" : 3,
        "forwardSecrecy" : true,
        "anonymous" : true,
        "serverKeyType" : "none"
      },
      {
        "id" : 49176,
        "name" : "ECDH_anon_WITH_AES_128_CBC_SHA",
        "strength" : 3,
        "forwardSecrecy" : true,
        "anonymous" : true,
        "serverKeyType" : "none"
      },
      {
        "id" : 49177,
        "name" : "ECDH_anon_WITH_AES_256_CBC_SHA",
        "strength" : 3,
        "forwardSecrecy" : true,
        "anonymous" : true,
        "serverKeyType" : "none"
      },
      {
        "id" : 49191,
        "name" : "ECDHE_RSA_WITH_AES_128_CBC_SHA256",
        "strength" : 3,
        "forwardSecrecy" : true,
        "anonymous" : false,
        "serverKeyType" : "RSA"
      },
      {
        "id" : 49192,
        "name" : "ECDHE_RSA_WITH_AES_256_CBC_SHA384",
        "strength" : 3,
        "forwardSecrecy" : true,
        "anonymous" : false,
        "serverKeyType" : "RSA"
      },
      {
        "id" : 49199,
        "name" : "ECDHE_RSA_WITH_AES_128_GCM_SHA256",
        "strength" : 3,
        "forwardSecrecy" : true,
        "anonymous" : false,
        "serverKeyType" : "RSA"
      },
      {
        "id" : 49200,
        "name" : "ECDHE_RSA_WITH_AES_256_GCM_SHA384",
        "strength" : 3,
        "forwardSecrecy" : true,
        "anonymous" : false,
        "serverKeyType" : "RSA"
      }
    ]
  },
  "ssl3Chains" : [
    {
      "length" : 1,
      "decoded" : true,
      "namesMatch" : true,
      "includesRoot" : true,
      "signHashes" : [
      ],
      "certificates" : [
        {
          "thumbprint" : "77F33D0F5C7BCCBF5C9C397F95FEE68C37E3C760",
          "decodable" : true,
          "serialHex" : "0144D89261",
          "subject" : "EMAILADDRESS=ssl@server.javatpoint.com,CN=server.javatpoint.com",
          "issuer" : "EMAILADDRESS=ssl@server.javatpoint.com,CN=server.javatpoint.com",
          "validFrom" : "2016-01-20 18:28:17 UTC",
          "validTo" : "2017-01-19 18:28:17 UTC",
          "keyType" : "RSA",
          "keySize" : 2048,
          "signHash" : "SHA-256",
          "selfIssued" : true,
          "serverNames" : [
            "server.javatpoint.com"
          ]
        }
      ]
    }
  ],
  "deflateCompress" : false,
  "serverTime" : "2016-04-24 05:55:36 UTC",
  "serverTimeOffsetMillis" : -13424,
  "secureRenegotiation" : true,
  "minECSize" : 256,
  "minECSizeExt" : 256,
  "namedCurves" : [
    {
      "name" : "secp256r1 (P-256)",
      "size" : 256,
      "spontaneous" : true
    }
  ],
  "warnings" : [
    {
      "id" : "CS005",
      "text" : "Server supports RC4."
    },
    {
      "id" : "CS006",
      "text" : "Server supports cipher suites with no forward secrecy."
    }
  ]
}
